deepnlp/__init__.py
deepnlp/api_service.py
deepnlp/dict_util.py
deepnlp/downloader.py
deepnlp/model_util.py
deepnlp/ner_tagger.py
deepnlp/nn_parser.py
deepnlp/pipeline.py
deepnlp/pos_tagger.py
deepnlp/segmenter.py
deepnlp/ner/__init__.py
deepnlp/ner/ner_model.py
deepnlp/ner/ner_model_bilstm.py
deepnlp/ner/ner_model_bilstm_crf.py
deepnlp/ner/reader.py
deepnlp/ner/data/models.conf
deepnlp/ner/data/zh/tag_to_id
deepnlp/ner/data/zh/word_to_id
deepnlp/ner/data/zh_entertainment/tag_to_id
deepnlp/ner/data/zh_entertainment/word_to_id
deepnlp/ner/data/zh_o2o/tag_to_id
deepnlp/ner/data/zh_o2o/word_to_id
deepnlp/ner/dict/zh/entity_tags.dic.pkl
deepnlp/ner/dict/zh_o2o/entity_tags.dic.pkl
deepnlp/parse/__init__.py
deepnlp/parse/beam_search.py
deepnlp/parse/parse_model.py
deepnlp/parse/predict.py
deepnlp/parse/reader.py
deepnlp/parse/transition_system.py
deepnlp/parse/data/models.conf
deepnlp/parse/data/zh/label_dict
deepnlp/parse/data/zh/parse.template
deepnlp/parse/data/zh/pos_dict
deepnlp/parse/data/zh/vocab_dict
deepnlp/pos/__init__.py
deepnlp/pos/pos_model.py
deepnlp/pos/pos_model_bilstm.py
deepnlp/pos/pos_model_bilstm_crf.py
deepnlp/pos/reader.py
deepnlp/pos/trainPOSModel.sh
deepnlp/pos/ckpt/zh/checkpoint
deepnlp/pos/ckpt/zh/pos.ckpt.data-00000-of-00001
deepnlp/pos/ckpt/zh/pos.ckpt.index
deepnlp/pos/ckpt/zh/pos.ckpt.meta
deepnlp/pos/data/models.conf
deepnlp/pos/data/zh/tag_to_id
deepnlp/pos/data/zh/word_to_id
deepnlp/segment/__init__.py
deepnlp/segment/data_util.py
deepnlp/segment/install_crfpp.sh
deepnlp/segment/train_crf.sh
deepnlp/segment/data/zh/template
deepnlp/segment/models/zh/crf_model
deepnlp/textrank/__init__.py
deepnlp/textrank/docs.txt
deepnlp/textrank/test_textrank.py
deepnlp/textrank/textrank.py
deepnlp-0.1.7.dist-info/DESCRIPTION.rst
deepnlp-0.1.7.dist-info/METADATA
deepnlp-0.1.7.dist-info/RECORD
deepnlp-0.1.7.dist-info/WHEEL
deepnlp-0.1.7.dist-info/metadata.json
deepnlp-0.1.7.dist-info/top_level.txt
