Metadata-Version: 2.0
Name: deepnlp
Version: 0.1.7
Summary: Deep Learning NLP Pipeline implemented on Tensorflow
Home-page: https://github.com/rockingdingo/deepnlp
Author: Xichen Ding
Author-email: dingo0927@126.com
License: MIT
Keywords: DeepLearning NLP Tensorflow deepnlp.org
Platform: UNKNOWN
Classifier: Development Status :: 4 - Beta
Classifier: Programming Language :: Python :: 2.7
Classifier: Programming Language :: Python :: 3
Classifier: Topic :: Scientific/Engineering
Classifier: Topic :: Software Development
Classifier: Topic :: Scientific/Engineering :: Artificial Intelligence
Requires: numpy
Requires: tensorflow
Requires: CRFPP
